cht_meteo/__init__.py
cht_meteo/coamps_tc_forecast_s3.py
cht_meteo/database.py
cht_meteo/dataset.py
cht_meteo/dataset_to_delft3d.py
cht_meteo/dataset_to_json_wind.py
cht_meteo/gfs_anl_0p50.py
cht_meteo/gfs_forecast_0p25.py
cht_meteo-0.3.1.dist-info/LICENSE
cht_meteo-0.3.1.dist-info/METADATA
cht_meteo-0.3.1.dist-info/WHEEL
cht_meteo-0.3.1.dist-info/top_level.txt
cht_meteo-0.3.1.dist-info/zip-safe
cht_meteo-0.3.1.dist-info/RECORD
